<annotation>
	<folder>test_resized</folder>
	<filename>00445811-00000095.jpg</filename>
	<path>D:\Data Science\Omdena\Asphalt\tongzheng_resized_dataset\resized_dataset\test_resized\00445811-00000095.jpg</path>
	<source>
		<database>Unknown</database>
	</source>
	<size>
		<width>512</width>
		<height>512</height>
		<depth>1</depth>
	</size>
	<segmented>0</segmented>
	<object>
		<name>Rut</name>
		<pose>Unspecified</pose>
		<truncated>1</truncated>
		<difficult>0</difficult>
		<bndbox>
			<xmin>159</xmin>
			<ymin>3</ymin>
			<xmax>211</xmax>
			<ymax>512</ymax>
		</bndbox>
	</object>
</annotation>
