<annotation>
	<folder>images</folder>
	<filename>01042094-00006568.jpg</filename>
	<path>C:\Users\vojed\Documents\Python Scripts\data\validation\images\01042094-00006568.jpg</path>
	<source>
		<database>Unknown</database>
	</source>
	<size>
		<width>2048</width>
		<height>1024</height>
		<depth>1</depth>
	</size>
	<segmented>0</segmented>
	<object>
		<name>Repair area</name>
		<pose>Unspecified</pose>
		<truncated>1</truncated>
		<difficult>0</difficult>
		<bndbox>
			<xmin>659</xmin>
			<ymin>830</ymin>
			<xmax>1992</xmax>
			<ymax>1024</ymax>
		</bndbox>
	</object>
	<object>
		<name>Repair area</name>
		<pose>Unspecified</pose>
		<truncated>1</truncated>
		<difficult>0</difficult>
		<bndbox>
			<xmin>9</xmin>
			<ymin>963</ymin>
			<xmax>276</xmax>
			<ymax>1024</ymax>
		</bndbox>
	</object>
</annotation>
