<annotation>
	<folder>vico_images</folder>
	<filename>00072933-00003113.jpg</filename>
	<path>/home/vico/Documents/OMDENA/project_01/vico_images/00072933-00003113.jpg</path>
	<source>
		<database>Unknown</database>
	</source>
	<size>
		<width>512</width>
		<height>512</height>
		<depth>1</depth>
	</size>
	<segmented>0</segmented>
	<object>
		<name>Pothole</name>
		<pose>Unspecified</pose>
		<truncated>0</truncated>
		<difficult>0</difficult>
		<bndbox>
			<xmin>308</xmin>
			<ymin>346</ymin>
			<xmax>352</xmax>
			<ymax>377</ymax>
		</bndbox>
	</object>
	<object>
		<name>Pothole</name>
		<pose>Unspecified</pose>
		<truncated>0</truncated>
		<difficult>0</difficult>
		<bndbox>
			<xmin>383</xmin>
			<ymin>376</ymin>
			<xmax>410</xmax>
			<ymax>403</ymax>
		</bndbox>
	</object>
	<object>
		<name>Lateral crack</name>
		<pose>Unspecified</pose>
		<truncated>0</truncated>
		<difficult>0</difficult>
		<bndbox>
			<xmin>221</xmin>
			<ymin>324</ymin>
			<xmax>297</xmax>
			<ymax>359</ymax>
		</bndbox>
	</object>
	<object>
		<name>Lateral crack</name>
		<pose>Unspecified</pose>
		<truncated>0</truncated>
		<difficult>0</difficult>
		<bndbox>
			<xmin>422</xmin>
			<ymin>371</ymin>
			<xmax>494</xmax>
			<ymax>416</ymax>
		</bndbox>
	</object>
</annotation>
