<annotation>
	<folder>test_resized</folder>
	<filename>00614735-00008767.jpg</filename>
	<path>D:\Data Science\Omdena\Asphalt\tongzheng_resized_dataset\resized_dataset\test_resized\00614735-00008767.jpg</path>
	<source>
		<database>Unknown</database>
	</source>
	<size>
		<width>512</width>
		<height>512</height>
		<depth>1</depth>
	</size>
	<segmented>0</segmented>
	<object>
		<name>Pothole</name>
		<pose>Unspecified</pose>
		<truncated>0</truncated>
		<difficult>0</difficult>
		<bndbox>
			<xmin>206</xmin>
			<ymin>271</ymin>
			<xmax>247</xmax>
			<ymax>315</ymax>
		</bndbox>
	</object>
	<object>
		<name>Pothole</name>
		<pose>Unspecified</pose>
		<truncated>0</truncated>
		<difficult>0</difficult>
		<bndbox>
			<xmin>168</xmin>
			<ymin>461</ymin>
			<xmax>207</xmax>
			<ymax>511</ymax>
		</bndbox>
	</object>
</annotation>
